mloda/community/compute_frameworks/example/__init__.py
mloda/community/compute_frameworks/example/community_example_compute_framework.py
mloda/community/extenders/example/__init__.py
mloda/community/extenders/example/community_example_extender.py
mloda/community/feature_groups/example/__init__.py
mloda/community/feature_groups/example/community_example_feature_group.py
mloda/community/feature_groups/example/example_a/__init__.py
mloda/community/feature_groups/example/example_a/example_a_feature_group.py
mloda/community/feature_groups/example/example_b/__init__.py
mloda/community/feature_groups/example/example_b/example_b_feature_group.py
mloda_community-0.2.6.dist-info/METADATA
mloda_community-0.2.6.dist-info/WHEEL
mloda_community-0.2.6.dist-info/top_level.txt
mloda_community-0.2.6.dist-info/RECORD
